ShockCalendar
