Metadata-Version: 1.0
Name: ShockCalendar
Version: 0.2.1
Summary: Un widget calendario para usar en Tkinter
Home-page: http://foro.el-hacker.com/miembros/sokoleonardo/
Author: adrian_leonardo_05 at hotmail.com.ar
Author-email: adrian_leonardo_05@hotmail.com.ar
License: MIT
Keywords: Tkinter,widget,calendar,date,time,canvas,GUI
Platform: UNKNOWN
